talwar/__init__.py
talwar/agent.py
talwar/analytics.py
talwar/constants.py
talwar/llm.py
talwar/logger.py
talwar/parser.py
talwar/planner.py
talwar/proxy.py
talwar/reporter.py
talwar/run.py
talwar/scanner.py
talwar/summarizer.py
talwar/tools.py
talwar/utils.py
talwar-0.1.3.dist-info/licenses/LICENSE
talwar-0.1.3.dist-info/METADATA
talwar-0.1.3.dist-info/WHEEL
talwar-0.1.3.dist-info/entry_points.txt
talwar-0.1.3.dist-info/top_level.txt
talwar-0.1.3.dist-info/RECORD
