Metadata-Version: 2.4
Name: talwar
Version: 0.1.3
Summary: AI-powered web application security testing tool
Author: anon
Author-email: anon <anontech100@gmail.com>
License: GNU GENERAL PUBLIC LICENSE
Classifier: Development Status :: 3 - Alpha
Classifier: Intended Audience :: Information Technology
Classifier: License :: OSI Approved :: MIT License
Classifier: Operating System :: OS Independent
Classifier: Programming Language :: Python :: 3
Classifier: Programming Language :: Python :: 3.9
Classifier: Programming Language :: Python :: 3.10
Classifier: Programming Language :: Python :: 3.11
Classifier: Topic :: Security
Classifier: Topic :: Software Development :: Testing
Requires-Python: >=3.9
License-File: LICENSE
Requires-Dist: anthropic>=0.47
Requires-Dist: beautifulsoup4>=4.13
Requires-Dist: colorama>=0.4
Requires-Dist: openai>=1.6
Requires-Dist: playwright>=1.40
Requires-Dist: PyYAML>=6.0
Requires-Dist: requests>=2.32
Requires-Dist: tiktoken>=0.9
Requires-Dist: posthog>=3.0.0
Provides-Extra: dev
Requires-Dist: pytest>=7.0.0; extra == "dev"
Requires-Dist: black>=23.0.0; extra == "dev"
Requires-Dist: isort>=5.0.0; extra == "dev"
Dynamic: author
Dynamic: license-file
Dynamic: requires-python
